streamlit_keywords/__init__.py
streamlit_keywords/frontend/build/asset-manifest.json
streamlit_keywords/frontend/build/bootstrap.min.css
streamlit_keywords/frontend/build/index.html
streamlit_keywords/frontend/build/static/js/main.946a22fe.js
streamlit_keywords/frontend/build/static/js/main.946a22fe.js.LICENSE.txt
streamlit_keywords/frontend/build/static/js/main.946a22fe.js.map
streamlit_keywords-0.1.12.dist-info/LICENSE
streamlit_keywords-0.1.12.dist-info/METADATA
streamlit_keywords-0.1.12.dist-info/WHEEL
streamlit_keywords-0.1.12.dist-info/top_level.txt
streamlit_keywords-0.1.12.dist-info/RECORD
