Metadata-Version: 2.2
Name: streamlit-keywords
Version: 0.1.12
Summary: A Streamlit custom component that provides enhanced usage over standard streamlit.multiselect. Users can enter free form text which will appear as separate keyword chips.
Author-email: Tyler House <26489166+tahouse@users.noreply.github.com>
License: Apache-2.0
Project-URL: Homepage, https://github.com/tahouse/streamlit-keywords
Project-URL: Documentation, https://github.com/tahouse/streamlit-keywords/blob/main/README.md
Project-URL: Issue Tracker, https://github.com/tahouse/streamlit-keywords/issues
Keywords: streamlit,component,multiselect,input,keywords,chips,material ui,tags
Classifier: Programming Language :: Python :: 3
Classifier: Programming Language :: Python :: 3.7
Classifier: License :: OSI Approved :: Apache Software License
Classifier: Operating System :: OS Independent
Classifier: Development Status :: 5 - Production/Stable
Classifier: Environment :: Web Environment
Classifier: Intended Audience :: Developers
Classifier: Topic :: Desktop Environment
Classifier: Topic :: Multimedia :: Graphics
Classifier: Topic :: Software Development :: User Interfaces
Requires-Python: >=3.7
License-File: LICENSE
Requires-Dist: streamlit>=0.63
Provides-Extra: devel
Requires-Dist: wheel; extra == "devel"
Requires-Dist: setuptools==69.0.3; extra == "devel"
Requires-Dist: pytest==7.4.0; extra == "devel"
Requires-Dist: twine~=6.1; extra == "devel"
Requires-Dist: packaging>=24.2; extra == "devel"
